pytradingview/__init__.py
pytradingview/__main__.py
pytradingview/chart.py
pytradingview/client.py
pytradingview/protocol.py
pytradingview/quote.py
pytradingview/utils.py
pytradingview-0.4.0.dist-info/licenses/LICENSE
pytradingview-0.4.0.dist-info/METADATA
pytradingview-0.4.0.dist-info/WHEEL
pytradingview-0.4.0.dist-info/entry_points.txt
pytradingview-0.4.0.dist-info/top_level.txt
pytradingview-0.4.0.dist-info/RECORD
