Metadata-Version: 2.4
Name: pytradingview
Version: 0.4.0
Summary: A Python client for TradingView WebSocket API. It's a lightweight library capable of providing real-time data on stocks, cryptocurrencies, indices etc.
Author-email: Onesimus Graves-Sampson <onesimusgravessampson1@gmail.com>
License-Expression: MIT
Project-URL: Homepage, https://github.com/kwesy/pytradingview.git
Keywords: tradingview,trading,forex,stocks,crypto
Requires-Python: >=3.8
License-File: LICENSE
Requires-Dist: websocket-client>=1.5.1
Requires-Dist: requests>=2.32.3
Dynamic: license-file
